colorp/__init__.py
colorp-0.0.1.dist-info/LICENSE
colorp-0.0.1.dist-info/METADATA
colorp-0.0.1.dist-info/WHEEL
colorp-0.0.1.dist-info/top_level.txt
colorp-0.0.1.dist-info/RECORD
