Metadata-Version: 2.1
Name: colorp
Version: 0.0.1
Summary: A small package for printing colored strings
Home-page: UNKNOWN
Author: Siddharth Gupta
Author-email: g.sidd97@gmail.com
License: UNKNOWN
Platform: UNKNOWN
Classifier: Programming Language :: Python :: 3
Classifier: License :: OSI Approved :: MIT License
Classifier: Operating System :: OS Independent
